{
  "id": "nd-companion",
  "type": "module",
  "title": "N&D Companion",
  "description": "DM Companion for Foundry VTT",
  "version": "0.1.18",

  "authors": [
    {
      "name": "Mo0sel"
    }
  ],

  "compatibility": {
    "minimum": "14",
    "verified": "14"
  },

  "esmodules": [
    "scripts/nd-companion.js"
  ],

  "styles": [
    "styles/nd-tokens.css",
    "styles/nd-components.css",
    "styles/nd-richtext.css",
    "styles/nd-layout.css",
    "styles/play.css",
    "styles/prepare.css",
    "styles/notes.css",
    "styles/nd-companion.css"
  ],

  "languages": [
    {
      "lang": "en",
      "name": "English",
      "path": "lang/en.json"
    }
  ],

  "manifest": "https://raw.githubusercontent.com/Mo0sel/nd-companion/main/module.json",
  "download": "https://github.com/Mo0sel/nd-companion/archive/refs/heads/main.zip",
  "url": "https://github.com/Mo0sel/nd-companion"
}